{
  "fechaActualizacion": "2026-01-28T14:12:47.364Z",
  "totalVideos": 3,
  "videos": [
    {
      "id": "xB4ecIksJSY",
      "title": "4. Git Push - Actualizar cambios de un repositorio local a remoto",
      "url": "https://www.youtube.com/watch?v=xB4ecIksJSY",
      "thumbnail": "https://i.ytimg.com/vi/xB4ecIksJSY/hqdefault.jpg",
      "publishedAt": "2026-01-24T12:04:21Z",
      "description": ""
    },
    {
      "id": "7bwkNrRpgw0",
      "title": "Modo oscuro - Big query - Google Cloud",
      "url": "https://www.youtube.com/watch?v=7bwkNrRpgw0",
      "thumbnail": "https://i.ytimg.com/vi/7bwkNrRpgw0/hqdefault.jpg",
      "publishedAt": "2026-01-23T06:52:23Z",
      "description": ""
    },
    {
      "id": "HDyKUodeuNw",
      "title": "Como seleccionar valores iguales en SQL",
      "url": "https://www.youtube.com/watch?v=HDyKUodeuNw",
      "thumbnail": "https://i.ytimg.com/vi/HDyKUodeuNw/hqdefault.jpg",
      "publishedAt": "2026-01-23T06:43:39Z",
      "description": ""
    }
  ]
}